alice/__init__.py
alice/alice.py
alice/language_models.py
alice_tool-0.0.1.dist-info/METADATA
alice_tool-0.0.1.dist-info/WHEEL
alice_tool-0.0.1.dist-info/top_level.txt
alice_tool-0.0.1.dist-info/RECORD
